prompt_siren/__init__.py
prompt_siren/agents/__init__.py
prompt_siren/agents/abstract.py
prompt_siren/agents/plain.py
prompt_siren/agents/registry.py
prompt_siren/agents/states.py
prompt_siren/agents/utils.py
prompt_siren/attacks/__init__.py
prompt_siren/attacks/abstract.py
prompt_siren/attacks/attack_utils.py
prompt_siren/attacks/dict_attack.py
prompt_siren/attacks/mini_goat_attack.py
prompt_siren/attacks/registry.py
prompt_siren/attacks/template_string_attack.py
prompt_siren/cli.py
prompt_siren/config/__init__.py
prompt_siren/config/default/attack/agentdojo_important_instructions.yaml
prompt_siren/config/default/attack/file.yaml
prompt_siren/config/default/attack/mini-goat.yaml
prompt_siren/config/default/config.yaml
prompt_siren/config/default/dataset/agentdojo-banking.yaml
prompt_siren/config/default/dataset/agentdojo-slack.yaml
prompt_siren/config/default/dataset/agentdojo-travel.yaml
prompt_siren/config/default/dataset/agentdojo-workspace.yaml
prompt_siren/config/default/dataset/swebench.yaml
prompt_siren/config/default/sandbox_manager/local-docker.yaml
prompt_siren/config/exceptions.py
prompt_siren/config/experiment_config.py
prompt_siren/config/export.py
prompt_siren/config/registry_bridge.py
prompt_siren/datasets/__init__.py
prompt_siren/datasets/abstract.py
prompt_siren/datasets/agentdojo_dataset.py
prompt_siren/datasets/registry.py
prompt_siren/datasets/swebench_dataset/__init__.py
prompt_siren/datasets/swebench_dataset/config.py
prompt_siren/datasets/swebench_dataset/constants.py
prompt_siren/datasets/swebench_dataset/dataset.py
prompt_siren/datasets/swebench_dataset/docker_builder.py
prompt_siren/datasets/swebench_dataset/dockerfiles/basic_agent/Dockerfile
prompt_siren/datasets/swebench_dataset/dockerfiles/exec_curl_bash_task/Dockerfile
prompt_siren/datasets/swebench_dataset/dockerfiles/exec_curl_bash_task/server.crt
prompt_siren/datasets/swebench_dataset/dockerfiles/exec_curl_bash_task/server.key
prompt_siren-0.0.1a2.dist-info/WHEEL
prompt_siren-0.0.1a2.dist-info/entry_points.txt
prompt_siren-0.0.1a2.dist-info/METADATA
prompt_siren-0.0.1a2.dist-info/RECORD
