Metadata-Version: 2.3
Name: prompt-siren
Version: 0.0.1a2
Summary: A research workbench for developing and testing attacks against large language models, with a focus on prompt injection vulnerabilities and defenses.
Author: Edoardo Debenedetti, Ivan Evtimov
Author-email: Edoardo Debenedetti <edoardo.debenedetti@inf.ethz.ch>
Classifier: Operating System :: POSIX :: Linux
Classifier: Operating System :: MacOS
Requires-Dist: aiohttp>=3.12.15
Requires-Dist: anyio>=4.10.0
Requires-Dist: click>=8.3.0
Requires-Dist: exceptiongroup>=1.2.0 ; python_full_version < '3.11'
Requires-Dist: backports-strenum>=1.3.1,<2.0 ; python_full_version < '3.11'
Requires-Dist: hydra-core>=1.3.2
Requires-Dist: hydra-submitit-launcher>=1.2.0
Requires-Dist: logfire>=4.7.0
Requires-Dist: pandas>=2.0.0
Requires-Dist: pydantic-ai-slim[anthropic,bedrock,google,openai]>=1.1.0
Requires-Dist: pyyaml>=6.0.2
Requires-Dist: opentelemetry-api>=1.20.0
Requires-Dist: opentelemetry-sdk>=1.20.0
Requires-Dist: opentelemetry-exporter-otlp>=1.20.0
Requires-Dist: omegaconf>=2.3.0
Requires-Dist: filelock>=3.19.1
Requires-Dist: tabulate>=0.9.0
Requires-Dist: typing-extensions>=4.15.0
Requires-Dist: openinference-instrumentation>=0.1.41
Requires-Dist: agentdojo>=0.1.35 ; extra == 'agentdojo'
Requires-Dist: prompt-siren[agentdojo,swebench,docker,playwright] ; extra == 'all'
Requires-Dist: aiodocker>=0.24.0 ; extra == 'docker'
Requires-Dist: playwright>=1.54.0 ; extra == 'playwright'
Requires-Dist: swebench ; extra == 'swebench'
Requires-Dist: jinja2>=3.1.6 ; extra == 'swebench'
Requires-Dist: black==25.12.0 ; extra == 'ufmt'
Requires-Dist: ruff-api==0.2.1 ; extra == 'ufmt'
Requires-Dist: stdlibs==2024.1.28 ; extra == 'ufmt'
Requires-Dist: ufmt==2.8.0 ; extra == 'ufmt'
Requires-Dist: usort==1.0.8.post1 ; extra == 'ufmt'
Requires-Python: >=3.10, <3.14
Provides-Extra: agentdojo
Provides-Extra: all
Provides-Extra: docker
Provides-Extra: playwright
Provides-Extra: swebench
Provides-Extra: ufmt
